mqtt_cli_subscriber-0.1.0.dist-info/DESCRIPTION.rst
mqtt_cli_subscriber-0.1.0.dist-info/METADATA
mqtt_cli_subscriber-0.1.0.dist-info/RECORD
mqtt_cli_subscriber-0.1.0.dist-info/WHEEL
mqtt_cli_subscriber-0.1.0.dist-info/entry_points.txt
mqtt_cli_subscriber-0.1.0.dist-info/metadata.json
mqtt_cli_subscriber-0.1.0.dist-info/top_level.txt
subscriber/__init__.py
