Metadata-Version: 2.0
Name: mqtt-cli-subscriber
Version: 0.1.0
Summary: Subscribe to messages from an MQTT broker using a command
Home-page: https://github.com/AndrewCarterUK/mqtt-cli-subscriber
Author: Andrew Carter
Author-email: andrewcarter1992@gmail.com
License: MIT
Keywords: mqtt subscriber
Platform: UNKNOWN
Classifier: Development Status :: 3 - Alpha
Classifier: Intended Audience :: Developers
Classifier: License :: OSI Approved :: MIT License
Classifier: Programming Language :: Python :: 2
Classifier: Programming Language :: Python :: 2.7
Classifier: Programming Language :: Python :: 3
Classifier: Programming Language :: Python :: 3.3
Classifier: Programming Language :: Python :: 3.4
Classifier: Programming Language :: Python :: 3.5
Requires-Dist: paho-mqtt
